chainos/__init__.py
chainos/commands/__init__.py
chainos/commands/chain.py
chainos/commands/cli.py
chainos/commands/run.py
chainos/commands/task.py
chainos/conf/__init__.py
chainos/conf/config.py
chainos/conf/settings.toml
chainos/core/__init__.py
chainos/core/run/__init__.py
chainos-0.1.0.dist-info/METADATA
chainos-0.1.0.dist-info/WHEEL
chainos-0.1.0.dist-info/entry_points.txt
chainos-0.1.0.dist-info/RECORD
