Metadata-Version: 2.1
Name: chainos
Version: 0.1.0
Summary: ChainOS-python is a python client for the ChainOS engine
Author: Brady
Author-email: bfendres@gmail.com
Requires-Python: >=3.10,<4.0
Classifier: Programming Language :: Python :: 3
Classifier: Programming Language :: Python :: 3.10
Classifier: Programming Language :: Python :: 3.11
Classifier: Programming Language :: Python :: 3.12
Requires-Dist: click (>=8.1.7,<9.0.0)
Requires-Dist: dynaconf (>=3.2.4,<4.0.0)
Requires-Dist: pydantic (>=2.6.1,<3.0.0)
Requires-Dist: requests (>=2.31.0,<3.0.0)
